cli/__init__.py
cli/main.py
indexgen-0.1.3.dist-info/LICENSE
indexgen-0.1.3.dist-info/METADATA
indexgen-0.1.3.dist-info/WHEEL
indexgen-0.1.3.dist-info/entry_points.txt
indexgen-0.1.3.dist-info/top_level.txt
indexgen-0.1.3.dist-info/RECORD
