Metadata-Version: 2.1
Name: indexgen
Version: 0.1.3
Summary: A utility CLI to generate a hyperlinked table of contents for your Git repositories, outputting as a navigable Markdown file.
Author: Aiman Fatima
Author-email: aimanfatimadl@gmail.com
License-File: LICENSE
Requires-Dist: Click
